util_ds/__init__.py
util_ds/log/__init__.py
util_ds/log/logger.py
util_ds/nlp/__init__.py
util_ds/nlp/japanese_parsing.py
util_ds/nlp/list.py
util_ds/nlp/ner.py
util_ds/nlp/os.py
util_ds/nlp/pos.py
util_ds/nlp/rouge_calculated.py
util_ds/nlp/sentence_token.py
util_ds/nlp/word_dictionary.py
util_ds/nlp/word_flag.py
util_ds/nlp/word_token.py
util_ds/nlp/Sumy/__init__.py
util_ds/nlp/Sumy/__main__.py
util_ds/nlp/Sumy/_compat.py
util_ds/nlp/Sumy/utils.py
util_ds/nlp/Sumy/evaluation/__init__.py
util_ds/nlp/Sumy/evaluation/__main__.py
util_ds/nlp/Sumy/evaluation/content_based.py
util_ds/nlp/Sumy/evaluation/coselection.py
util_ds/nlp/Sumy/evaluation/rouge.py
util_ds/nlp/Sumy/models/__init__.py
util_ds/nlp/Sumy/models/tf.py
util_ds/nlp/Sumy/models/dom/__init__.py
util_ds/nlp/Sumy/models/dom/_document.py
util_ds/nlp/Sumy/models/dom/_paragraph.py
util_ds/nlp/Sumy/models/dom/_sentence.py
util_ds/nlp/Sumy/nlp/__init__.py
util_ds/nlp/Sumy/nlp/tokenizers.py
util_ds/nlp/Sumy/nlp/stemmers/__init__.py
util_ds/nlp/Sumy/nlp/stemmers/czech.py
util_ds/nlp/Sumy/parsers/__init__.py
util_ds/nlp/Sumy/parsers/html.py
util_ds/nlp/Sumy/parsers/parser.py
util_ds/nlp/Sumy/parsers/plaintext.py
util_ds/nlp/Sumy/similarity/__init__.py
util_ds/nlp/Sumy/similarity/cosine_sim.py
util_ds/nlp/Sumy/summarizers/__init__.py
util_ds/nlp/Sumy/summarizers/_summarizer.py
util_ds/nlp/Sumy/summarizers/edmundson.py
util_ds/nlp/Sumy/summarizers/edmundson_cue.py
util_ds/nlp/Sumy/summarizers/edmundson_key.py
util_ds/nlp/Sumy/summarizers/edmundson_location.py
util_ds/nlp/Sumy/summarizers/edmundson_title.py
util_ds/nlp/Sumy/summarizers/kl.py
util_ds/nlp/Sumy/summarizers/lex_rank.py
util_ds/nlp/Sumy/summarizers/lsa.py
util_ds/nlp/Sumy/summarizers/luhn.py
util_ds/nlp/Sumy/summarizers/random.py
util_ds/nlp/Sumy/summarizers/submodular.py
util_ds/nlp/Sumy/summarizers/sum_basic.py
util_ds/nlp/Sumy/summarizers/text_rank.py
util_ds/nlp/rouge/__init__.py
util_ds/nlp/rouge/rouge.py
util_ds/nlp/rouge/rouge_score.py
util_ds-0.5.3.dist-info/LICENSE
util_ds-0.5.3.dist-info/METADATA
util_ds-0.5.3.dist-info/WHEEL
util_ds-0.5.3.dist-info/top_level.txt
util_ds-0.5.3.dist-info/RECORD
